lopace/__init__.py
lopace/_version.py
lopace/compressor.py
lopace-0.1.5.dist-info/licenses/LICENSE
scripts/README.md
scripts/__init__.py
scripts/generate_visualizations.py
scripts/requirements.txt
tests/__init__.py
tests/test_compressor.py
lopace-0.1.5.dist-info/METADATA
lopace-0.1.5.dist-info/WHEEL
lopace-0.1.5.dist-info/top_level.txt
lopace-0.1.5.dist-info/RECORD
