Metadata-Version: 2.4
Name: lopace
Version: 0.1.5
Summary: Lossless Optimized Prompt Accurate Compression Engine
Home-page: https://github.com/connectaman/LoPace
Author: Aman Ulla
License: MIT
Project-URL: Homepage, https://github.com/connectaman/LoPace
Project-URL: Repository, https://github.com/connectaman/LoPace
Project-URL: Issues, https://github.com/connectaman/LoPace/issues
Project-URL: PyPI, https://pypi.org/project/lopace/
Project-URL: Hugging Face Spaces, https://huggingface.co/spaces/codewithaman/LoPace
Keywords: prompt,compression,tokenization,zstd,bpe,nlp
Classifier: Development Status :: 4 - Beta
Classifier: Intended Audience :: Developers
Classifier: Topic :: Software Development :: Libraries :: Python Modules
Classifier: Topic :: Text Processing :: Linguistic
Classifier: License :: OSI Approved :: MIT License
Classifier: Programming Language :: Python :: 3
Classifier: Programming Language :: Python :: 3.8
Classifier: Programming Language :: Python :: 3.9
Classifier: Programming Language :: Python :: 3.10
Classifier: Programming Language :: Python :: 3.11
Classifier: Programming Language :: Python :: 3.12
Requires-Python: >=3.8
License-File: LICENSE
Requires-Dist: zstandard>=0.22.0
Requires-Dist: tiktoken>=0.5.0
Dynamic: home-page
Dynamic: license-file
Dynamic: requires-python
